bidscycle/.DS_Store
bidscycle/__init__.py
bidscycle/clean_duplicates.py
bidscycle/create_duplicates.py
bidscycle/switch_duplicate.py
bidscycle/cli/__init__.py
bidscycle/cli/run.py
bidscycle-0.0.2.dist-info/entry_points.txt
bidscycle-0.0.2.dist-info/licenses/LICENSE
bidscycle-0.0.2.dist-info/WHEEL
bidscycle-0.0.2.dist-info/METADATA
bidscycle-0.0.2.dist-info/RECORD
