Metadata-Version: 2.4
Name: BIDScycle
Version: 0.0.2
Summary: Easy BIDS compliant renaming of BIDS duplicates
Author-email: Milton Camacho <miltoncamachoicc@gmail.com>, Shireen Parimoo <sparimoo95@gmail.com>
Requires-Python: >=3.11.1
Classifier: Development Status :: 3 - Alpha
Classifier: Intended Audience :: Developers
Classifier: License :: OSI Approved :: MIT License
Classifier: Programming Language :: Python :: 3 :: Only
Classifier: Programming Language :: Python :: 3.8
Classifier: Programming Language :: Python :: 3.9
Classifier: Programming Language :: Python :: 3.10
Classifier: Programming Language :: Python :: 3.11
License-File: LICENSE
Requires-Dist: pybids
Requires-Dist: coloredlogs
Requires-Dist: pandas
Requires-Dist: datalad
Requires-Dist: pyspark>=3.0.0 ; extra == "spark"
Requires-Dist: bandit[toml]==1.8.3 ; extra == "test"
Requires-Dist: black==25.1.0 ; extra == "test"
Requires-Dist: check-manifest==0.50 ; extra == "test"
Requires-Dist: flake8-bugbear==24.12.12 ; extra == "test"
Requires-Dist: flake8-docstrings ; extra == "test"
Requires-Dist: flake8-formatter_junit_xml ; extra == "test"
Requires-Dist: flake8 ; extra == "test"
Requires-Dist: flake8-pyproject ; extra == "test"
Requires-Dist: pre-commit==4.2.0 ; extra == "test"
Requires-Dist: pylint==3.3.7 ; extra == "test"
Requires-Dist: pylint_junit ; extra == "test"
Requires-Dist: pytest-cov==6.1.1 ; extra == "test"
Requires-Dist: pytest-mock<3.14.1 ; extra == "test"
Requires-Dist: pytest-runner ; extra == "test"
Requires-Dist: pytest==8.3.5 ; extra == "test"
Requires-Dist: pytest-github-actions-annotate-failures ; extra == "test"
Requires-Dist: shellcheck-py==0.10.0.1 ; extra == "test"
Project-URL: Documentation, https://github.com/miltoncamacho/bidscycle/tree/main#readme
Project-URL: Source, https://github.com/miltoncamacho/bidscycle
Project-URL: Tracker, https://github.com/miltoncamacho/bidscycle/issues
Provides-Extra: spark
Provides-Extra: test
